pulse_coupled_nn/__init__.py
pulse_coupled_nn/classic_model.py
pulse_coupled_nn/flm_model.py
pulse_coupled_nn/general_model.py
pulse_coupled_nn/icm_model.py
pulse_coupled_nn/kernels.py
pulse_coupled_nn/mlm_model.py
pulse_coupled_nn/scm_model.py
pulse_coupled_nn/simulator.py
pulse_coupled_nn/slm_model.py
pulse_coupled_nn/test_run.py
pulse_coupled_nn/test_show.py
src/__init__.py
src/classic_model.py
src/flm_model.py
src/general_model.py
src/icm_model.py
src/kernels.py
src/mlm_model.py
src/scm_model.py
src/simulator.py
src/slm_model.py
src/test_show.py
pulse_coupled_nn-0.0.6.dist-info/LICENSE.txt
pulse_coupled_nn-0.0.6.dist-info/METADATA
pulse_coupled_nn-0.0.6.dist-info/WHEEL
pulse_coupled_nn-0.0.6.dist-info/top_level.txt
pulse_coupled_nn-0.0.6.dist-info/RECORD
