Metadata-Version: 2.1
Name: pulse-coupled-nn
Version: 0.0.6
Summary: Python implementation of the Pulse Coupled Neural Network (PCNN)
Home-page: https://github.com/ArdeleanRichard/PCNN
Author: Eugen-Richard Ardelean
Author-email: ardeleaneugenrichard@gmail.com
License: MIT
Platform: UNKNOWN
Classifier: License :: OSI Approved :: MIT License
Classifier: Programming Language :: Python :: 3.7
Classifier: Operating System :: OS Independent
Requires-Python: >=3.7
Requires-Dist: numpy
Requires-Dist: scipy
Requires-Dist: matplotlib
Requires-Dist: astropy
Provides-Extra: dev
Requires-Dist: twine >=4.0.2 ; extra == 'dev'
